dataflows/VERSION
dataflows/__init__.py
dataflows/cli.py
dataflows/base/__init__.py
dataflows/base/datastream.py
dataflows/base/datastream_processor.py
dataflows/base/exceptions.py
dataflows/base/flow.py
dataflows/base/package_wrapper.py
dataflows/base/resource_wrapper.py
dataflows/base/schema_validator.py
dataflows/helpers/__init__.py
dataflows/helpers/datapackage_processor.py
dataflows/helpers/extended_json.py
dataflows/helpers/iterable_loader.py
dataflows/helpers/resource_matcher.py
dataflows/helpers/resources_processor.py
dataflows/helpers/row_processor.py
dataflows/helpers/rows_processor.py
dataflows/processors/__init__.py
dataflows/processors/add_computed_field.py
dataflows/processors/add_field.py
dataflows/processors/checkpoint.py
dataflows/processors/concatenate.py
dataflows/processors/conditional.py
dataflows/processors/deduplicate.py
dataflows/processors/delete_fields.py
dataflows/processors/delete_resource.py
dataflows/processors/duplicate.py
dataflows/processors/filter_rows.py
dataflows/processors/finalizer.py
dataflows/processors/find_replace.py
dataflows/processors/join.py
dataflows/processors/load.py
dataflows/processors/parallelize.py
dataflows/processors/printer.py
dataflows/processors/rename_fields.py
dataflows/processors/select_fields.py
dataflows/processors/set_primary_key.py
dataflows/processors/set_type.py
dataflows/processors/sort_rows.py
dataflows/processors/sources.py
dataflows/processors/stream.py
dataflows/processors/unpivot.py
dataflows/processors/unstream.py
dataflows/processors/update_package.py
dataflows/processors/update_resource.py
dataflows/processors/update_schema.py
dataflows/processors/update_stats.py
dataflows/processors/validate.py
dataflows/processors/dumpers/__init__.py
dataflows/processors/dumpers/dumper_base.py
dataflows/processors/dumpers/file_dumper.py
dataflows/processors/dumpers/to_path.py
dataflows/processors/dumpers/to_sql.py
dataflows/processors/dumpers/to_zip.py
dataflows/processors/dumpers/formats/__init__.py
dataflows-0.5.12.dist-info/LICENSE
dataflows-0.5.12.dist-info/METADATA
dataflows-0.5.12.dist-info/WHEEL
dataflows-0.5.12.dist-info/entry_points.txt
dataflows-0.5.12.dist-info/top_level.txt
dataflows-0.5.12.dist-info/RECORD
