Metadata-Version: 2.1
Name: dataflows
Version: 0.5.12
Summary: A nifty data processing framework, based on data packages
Home-page: https://github.com/datahq/dataflows
Author: Adam Kariv
Author-email: adam.kariv@gmail.com
License: MIT
Keywords: data
Platform: UNKNOWN
Classifier: Development Status :: 4 - Beta
Classifier: Intended Audience :: Developers
Classifier: License :: OSI Approved :: MIT License
Classifier: Operating System :: OS Independent
Classifier: Programming Language :: Python :: 3.12
Classifier: Topic :: Software Development :: Libraries :: Python Modules
Requires-Dist: dataflows-tabulator>=1.54.0
Requires-Dist: datapackage>=1.15.4
Requires-Dist: tableschema>=1.21.0
Requires-Dist: kvfile>=1.1.1
Requires-Dist: click
Requires-Dist: jinja2
Requires-Dist: awesome-slugify
Requires-Dist: inquirer
Requires-Dist: tabulate
Requires-Dist: tableschema-sql>=2.0.1
Requires-Dist: xmljson
Requires-Dist: bitstring>=3
Requires-Dist: python-dateutil
Requires-Dist: openpyxl
Provides-Extra: develop
Requires-Dist: pylama; extra == "develop"
Requires-Dist: pylama-quotes; extra == "develop"
Requires-Dist: pyflakes<2.5; extra == "develop"
Requires-Dist: setuptools; extra == "develop"
Requires-Dist: mock; extra == "develop"
Requires-Dist: pytest; extra == "develop"
Requires-Dist: pytest-cov; extra == "develop"
Requires-Dist: coverage; extra == "develop"
Requires-Dist: lxml; extra == "develop"
Provides-Extra: speedup
Requires-Dist: plyvel; extra == "speedup"
